moog_sub37_mcp/__init__.py
moog_sub37_mcp/main.py
moog_sub37_mcp/mcp_server/__init__.py
moog_sub37_mcp/mcp_server/server.py
moog_sub37_mcp/midi/__init__.py
moog_sub37_mcp/midi/midi_manager.py
moog_sub37_mcp/tools/__init__.py
moog_sub37_mcp/tools/amp_tool.py
moog_sub37_mcp/tools/arp_tool.py
moog_sub37_mcp/tools/filter_tool.py
moog_sub37_mcp/tools/fx_tool.py
moog_sub37_mcp/tools/glide_tool.py
moog_sub37_mcp/tools/global_tool.py
moog_sub37_mcp/tools/lfo_tool.py
moog_sub37_mcp/tools/mod_tool.py
moog_sub37_mcp/tools/osc_tool.py
moog_sub37_mcp-0.0.5.dist-info/METADATA
moog_sub37_mcp-0.0.5.dist-info/WHEEL
moog_sub37_mcp-0.0.5.dist-info/entry_points.txt
moog_sub37_mcp-0.0.5.dist-info/RECORD
