Metadata-Version: 2.4
Name: moog-sub37-mcp
Version: 0.0.5
Summary: MPC to control Moog Sub37 Monophonic Synthesizer
Project-URL: Homepage, https://github.com/zerubeus/moog-sub37-mcp
Project-URL: Bug Tracker, https://github.com/zerubeus/moog-sub37-mcp/issues
Author-email: zerubeus <zerubeus@gmail.com>
License-Expression: MIT
Classifier: Development Status :: 4 - Beta
Classifier: Intended Audience :: Developers
Classifier: Intended Audience :: Information Technology
Classifier: License :: OSI Approved :: MIT License
Classifier: Operating System :: OS Independent
Classifier: Programming Language :: Python
Classifier: Programming Language :: Python :: 3.12
Classifier: Topic :: Internet
Classifier: Topic :: Scientific/Engineering :: Artificial Intelligence
Classifier: Topic :: Software Development :: Libraries :: Python Modules
Requires-Python: >=3.12
Requires-Dist: mcp[cli]>=1.5.0
Requires-Dist: mido>=1.3.1
Requires-Dist: pydantic>=2.10.6
Requires-Dist: python-rtmidi>=1.5.7
